Metadata-Version: 2.1
Name: pyweidentity
Version: 2.0.0
Summary: UNKNOWN
Home-page: https://github.com/99Kies/Weidentity-Python-SDK
Author: 99Kies
Author-email: 1290017556@qq.com
License: UNKNOWN
Platform: UNKNOWN
Classifier: Programming Language :: Python :: 3
Classifier: License :: OSI Approved :: Apache Software License
Classifier: Operating System :: OS Independent
